ru_text_cleaner/__init__.py
ru_text_cleaner/simple_cleaner/TextCleaner.py
ru_text_cleaner/simple_cleaner/__init__.py
ru_text_cleaner/simple_cleaner/_clean_stopwords.py
ru_text_cleaner/simple_cleaner/_emoji_cleaner.py
ru_text_cleaner/simple_cleaner/_html_cleaner.py
ru_text_cleaner/simple_cleaner/_punctuation_cleaner.py
ru_text_cleaner/simple_cleaner/_spaces_cleaner.py
ru_text_cleaner/simple_cleaner/_to_lower.py
ru_text_cleaner/simple_cleaner/_to_morpheme.py
ru_text_cleaner-2.0.3.dist-info/METADATA
ru_text_cleaner-2.0.3.dist-info/WHEEL
ru_text_cleaner-2.0.3.dist-info/licenses/LICENSE
ru_text_cleaner-2.0.3.dist-info/RECORD
