Metadata-Version: 2.3
Name: ru-text-cleaner
Version: 2.0.3
Summary: Cleans russian text and preparing for NLP
Project-URL: Homepage, https://github.com/rvneural/TextCleaner
Project-URL: Issues, https://github.com/rvneural/TextCleaner/issues
Author: Vildan Nasyrov
Author-email: Artem Gafarov <a.m.gafarov@ya.ru>
License-File: LICENSE
Classifier: License :: OSI Approved :: MIT License
Classifier: Operating System :: OS Independent
Classifier: Programming Language :: Python :: 3
Requires-Python: >=3.10.4
